featmongo/serializer.py
featmongo/__init__.py
featmongo/document.py
featmongo-0.1.0.dist-info/metadata.json
featmongo-0.1.0.dist-info/top_level.txt
featmongo-0.1.0.dist-info/DESCRIPTION.rst
featmongo-0.1.0.dist-info/METADATA
featmongo-0.1.0.dist-info/WHEEL
featmongo-0.1.0.dist-info/RECORD
