Metadata-Version: 2.0
Name: featmongo
Version: 0.1.0
Summary: Wrapper around pymongo using the serialization module of feat to convert BSON to python object 
Home-page: UNKNOWN
Author: Pragmatic Coders Developers
Author-email: dev@pragmaticcoders.com
License: Proprietary
Platform: any
Classifier: Development Status :: 4 - Beta
Classifier: Environment :: No Input/Output (Daemon)
Classifier: Natural Language :: English
Classifier: Operating System :: POSIX :: Linux
Classifier: Programming Language :: Python :: 2.6
Requires-Dist: pymongo
